{"train/train_return_nearest":1.7578,"train/train_games_heuristic":5,"train/clip_frac":0,"_wandb":{"runtime":4229},"train/train_games_snapshot_sample":5,"train/train_return_hellburner":-4.7934,"train/launch_rate":0.902344,"train/entropy_target":3.308789,"train/reward_terminal_time":0,"train/train_return_heuristic":-3.9123,"train/sps":1.6,"train/entropy_launch":0.023814,"train/train_win_rate_snapshot_sample":0.6,"train/ent_coef":0.04744,"train/train_games_hellburner":5,"train/entropy_source":0.68674,"_step":6400,"train/step":6400,"train/train_win_rate_nearest":0.8,"train/avg_send_bin":1.571429,"train/loss":-0.229251,"train/reward_production_delta":-0.002539,"train/reward_launch_penalty":-0.000711,"train/train_win_rate_heuristic":0,"train/train_win_rate_hellburner":0,"train/approx_kl":1e-06,"train/noop_rate":0.097656,"_timestamp":1.7799496251096838e+09,"train/explained_var":0.071801,"train/policy_loss":0,"train/mean_return_25":-1.6465,"train/reward_mean":-0.00325,"train/snapshot_pool_size":2,"train/entropy":5.280831,"train/train_return_snapshot_sample":0.3616,"train/entropy_send":1.326916,"train/train_games_nearest":5,"train/reward_terminal":0,"train/episode":20,"train/value_loss":0.042146,"train/lr":2.8e-05,"_runtime":4229.427553613,"train/update":25}